holidayskr/__init__.py
holidayskr/core.py
tests/__init__.py
tests/test_core.py
holidayskr-0.2.0.dist-info/LICENSE
holidayskr-0.2.0.dist-info/METADATA
holidayskr-0.2.0.dist-info/WHEEL
holidayskr-0.2.0.dist-info/top_level.txt
holidayskr-0.2.0.dist-info/RECORD
