Metadata-Version: 2.1
Name: holidayskr
Version: 0.2.0
Summary: 대한민국의 공휴일을 계산하는 Python 패키지입니다. 양음력 고휴일 뿐 아니라, 매년 변동되는 공휴일(대체 공휴일, 선거일 등)까지 포함하여 정확한 공휴일 정보를 제공합니다. 금일 혹은 특정 날짜가 공휴일인지 확인하거나, 주어진 연도의 모든 공휴일을 조회할 수 있습니다.
Home-page: https://github.com/6mini/holidayskr
Author: Yoonmin Lee
Author-email: real6mini@gmail.com
License: MIT
Keywords: Korea holidays lunar-calendar public-holidays
Classifier: Programming Language :: Python :: 3
Classifier: Programming Language :: Python :: 3.6
Classifier: Programming Language :: Python :: 3.7
Classifier: Programming Language :: Python :: 3.8
Classifier: Programming Language :: Python :: 3.9
Classifier: Programming Language :: Python :: 3.10
Classifier: License :: OSI Approved :: MIT License
Classifier: Operating System :: OS Independent
Classifier: Development Status :: 4 - Beta
Classifier: Intended Audience :: Developers
Classifier: Topic :: Software Development :: Libraries :: Python Modules
Classifier: Topic :: Office/Business :: Scheduling
Requires-Python: >=3.6
License-File: LICENSE
Requires-Dist: korean_lunar_calendar>=0.2.1
Requires-Dist: requests>=2.0.0
Provides-Extra: dev
Requires-Dist: pytest>=6.0.0; extra == "dev"
Requires-Dist: check-manifest; extra == "dev"
Requires-Dist: twine; extra == "dev"
